{
  "recentFiles": [
    {
      "basename": "butterworthMorganMikhailClinical2022",
      "path": "Reference folder/butterworthMorganMikhailClinical2022.md"
    },
    {
      "basename": "Labour analgesia",
      "path": "Labour analgesia.md"
    },
    {
      "basename": "Laprascopic surgery_Sum",
      "path": "Summaries/Anaesthesia summaries/Laprascopic surgery_Sum.md"
    },
    {
      "basename": "Laparoscopic surgery",
      "path": "Literature notes/Anaesthesia core notes/Domain 1_ Fundementals of Anaesthesia/Laparoscopic surgery.md"
    },
    {
      "basename": "Domain 1_Topics and links",
      "path": "Literature notes/Anaesthesia core notes/Domain 1_ Fundementals of Anaesthesia/Domain 1_Topics and links.md"
    },
    {
      "basename": "Domain 3_ Topics and links",
      "path": "Literature notes/Anaesthesia core notes/Domain 3_Obstetrics/Domain 3_ Topics and links.md"
    },
    {
      "basename": "Maternal conditions",
      "path": "Maternal conditions.md"
    },
    {
      "basename": "Non obstetric surgery",
      "path": "Non obstetric surgery.md"
    },
    {
      "basename": "Maternal collapse and CPR",
      "path": "Maternal collapse and CPR.md"
    },
    {
      "basename": "Maternal airway and GA",
      "path": "Maternal airway and GA.md"
    },
    {
      "basename": "Fetus and Placenta",
      "path": "Fetus and Placenta.md"
    },
    {
      "basename": "Lung function testing",
      "path": "Literature notes/Anaesthesia core notes/Domain 14_Paper 3_Data interpretation/Lung function testing.md"
    },
    {
      "basename": "Obstetric physiology",
      "path": "Literature notes/Anaesthesia core notes/Domain 3_Obstetrics/Obstetric physiology.md"
    },
    {
      "basename": "Domain 2_ Topics and links",
      "path": "Literature notes/Anaesthesia core notes/Domain 2_ Major and trauma surgery/Domain 2_ Topics and links.md"
    },
    {
      "basename": "Anaesthesia questions",
      "path": "Anaesthesia questions.md"
    },
    {
      "basename": "Cardiac_Disease_in_Pregnancy_Sum",
      "path": "Summaries/Anaesthesia summaries/Cardiac_Disease_in_Pregnancy_Sum.md"
    },
    {
      "basename": "Dunkman.Manning_EnhancedRecovery_2018 - Annotations (17042023, 092543)",
      "path": "Reference notes/Dunkman.Manning_EnhancedRecovery_2018 - Annotations (17042023, 092543).md"
    },
    {
      "basename": "@andersonRegistrybasedTrialsPotential2020",
      "path": "Reference notes/@andersonRegistrybasedTrialsPotential2020.md"
    },
    {
      "basename": "Cardiac disease in pregnancy",
      "path": "Literature notes/Anaesthesia core notes/Domain 3_Obstetrics/Cardiac disease in pregnancy.md"
    },
    {
      "basename": "Practical Protocols and recipes",
      "path": "Literature notes/Anaesthesia core notes/Domain 1_ Fundementals of Anaesthesia/Practical Protocols and recipes.md"
    },
    {
      "basename": "Anaesthetic management of specific cardiac conditions",
      "path": "Literature notes/Anaesthesia core notes/Domain 4_ Cardiac_Thoracic_Vascular/Anaesthetic management of specific cardiac conditions.md"
    },
    {
      "basename": "Domain 4_ Topics and links",
      "path": "Literature notes/Anaesthesia core notes/Domain 4_ Cardiac_Thoracic_Vascular/Domain 4_ Topics and links.md"
    },
    {
      "basename": "Anaesthesia Formulas",
      "path": "Literature notes/Anaesthesia core notes/Domain 1_ Fundementals of Anaesthesia/Anaesthesia Formulas.md"
    },
    {
      "basename": "Cardiac diseases",
      "path": "Cardiac diseases.md"
    },
    {
      "basename": "Dataview of literature",
      "path": "Dataview of literature.md"
    },
    {
      "basename": "Pulmonary Hypertension",
      "path": "Literature notes/Anaesthesia core notes/Domain 4_ Cardiac_Thoracic_Vascular/Pulmonary Hypertension.md"
    },
    {
      "basename": "ARDS",
      "path": "Literature notes/Anaesthesia core notes/Domain 8_ ICU/ARDS.md"
    },
    {
      "basename": "Tracheostomy",
      "path": "Literature notes/Anaesthesia core notes/Domain 8_ ICU/Tracheostomy.md"
    },
    {
      "basename": "Ventilation and Weaning",
      "path": "Literature notes/Anaesthesia core notes/Domain 8_ ICU/Ventilation and Weaning.md"
    },
    {
      "basename": "Fluids and volume status",
      "path": "Literature notes/Anaesthesia core notes/Domain 8_ ICU/Fluids and volume status.md"
    },
    {
      "basename": "Infection and antibiotics",
      "path": "Literature notes/Anaesthesia core notes/Domain 8_ ICU/Infection and antibiotics.md"
    },
    {
      "basename": "Domain 8_ Topics and links",
      "path": "Literature notes/Anaesthesia core notes/Domain 8_ ICU/Domain 8_ Topics and links.md"
    },
    {
      "basename": "General ICU",
      "path": "Literature notes/Anaesthesia core notes/Domain 8_ ICU/General ICU.md"
    },
    {
      "basename": "Hypertensive disease in pregnancy",
      "path": "Literature notes/Anaesthesia core notes/Domain 3_Obstetrics/Hypertensive disease in pregnancy.md"
    },
    {
      "basename": "Hypertensive disorders in pregnancy_Sum",
      "path": "Summaries/Anaesthesia summaries/Hypertensive disorders in pregnancy_Sum.md"
    },
    {
      "basename": "Physiological effects of pneumoperitoneum",
      "path": "Literature notes/Anaesthesia core notes/Domain 1_ Fundementals of Anaesthesia/Physiological effects of pneumoperitoneum.md"
    }
  ],
  "omittedPaths": [],
  "maxLength": null,
  "openType": "tab"
}