{
  "main": {
    "id": "b03620cd7620229b",
    "type": "split",
    "children": [
      {
        "id": "c3acffc14b3c7f3f",
        "type": "tabs",
        "children": [
          {
            "id": "08e1498bb3afc599",
            "type": "leaf",
            "state": {
              "type": "graph",
              "state": {}
            }
          }
        ]
      }
    ],
    "direction": "vertical"
  },
  "left": {
    "id": "64a76b8dd413a0a6",
    "type": "split",
    "children": [
      {
        "id": "cf220c1c3981febe",
        "type": "tabs",
        "children": [
          {
            "id": "a5905b0c2e77e213",
            "type": "leaf",
            "state": {
              "type": "recent-files",
              "state": {}
            }
          },
          {
            "id": "e7820bc7ab6b6565",
            "type": "leaf",
            "state": {
              "type": "file-explorer",
              "state": {
                "sortOrder": "alphabetical"
              }
            }
          },
          {
            "id": "1b344b8adde99a05",
            "type": "leaf",
            "state": {
              "type": "search",
              "state": {
                "query": "",
                "matchingCase": false,
                "explainSearch": false,
                "collapseAll": false,
                "extraContext": false,
                "sortOrder": "alphabetical"
              }
            }
          },
          {
            "id": "c22fb47e36ffc4b6",
            "type": "leaf",
            "state": {
              "type": "bookmarks",
              "state": {}
            }
          }
        ],
        "currentTab": 1
      }
    ],
    "direction": "horizontal",
    "width": 300
  },
  "right": {
    "id": "14819b09aaf6f876",
    "type": "split",
    "children": [
      {
        "id": "28b0c41120d8a157",
        "type": "tabs",
        "children": [
          {
            "id": "256ad89ce1ed674d",
            "type": "leaf",
            "state": {
              "type": "calendar",
              "state": {}
            }
          },
          {
            "id": "b0517e9dc6335235",
            "type": "leaf",
            "state": {
              "type": "backlink",
              "state": {
                "collapseAll": false,
                "extraContext": false,
                "sortOrder": "alphabetical",
                "showSearch": false,
                "searchQuery": "",
                "backlinkCollapsed": false,
                "unlinkedCollapsed": true
              }
            }
          },
          {
            "id": "055fe11e1af364a7",
            "type": "leaf",
            "state": {
              "type": "outgoing-link",
              "state": {
                "linksCollapsed": false,
                "unlinkedCollapsed": true
              }
            }
          },
          {
            "id": "86049ca635333614",
            "type": "leaf",
            "state": {
              "type": "tag",
              "state": {
                "sortOrder": "frequency",
                "useHierarchy": true
              }
            }
          },
          {
            "id": "26053c93384d574b",
            "type": "leaf",
            "state": {
              "type": "outline",
              "state": {}
            }
          },
          {
            "id": "78f91e5c06236412",
            "type": "leaf",
            "state": {
              "type": "ReferenceListView",
              "state": {}
            }
          },
          {
            "id": "0380c57a8d06e1cc",
            "type": "leaf",
            "state": {
              "type": "smart-connections-view",
              "state": {}
            }
          },
          {
            "id": "1e66be8860bef9ac",
            "type": "leaf",
            "state": {
              "type": "smart-connections-chat-view",
              "state": {}
            }
          }
        ],
        "currentTab": 7
      }
    ],
    "direction": "horizontal",
    "width": 300
  },
  "left-ribbon": {
    "hiddenItems": {
      "templater-obsidian:Templater": false,
      "switcher:Open quick switcher": false,
      "graph:Open graph view": false,
      "canvas:Create new canvas": false,
      "daily-notes:Open today's daily note": false,
      "templates:Insert template": false,
      "command-palette:Open command palette": false,
      "workspaces:Manage workspace layouts": false
    }
  },
  "active": "1e66be8860bef9ac",
  "lastOpenFiles": [
    "Cardiac diseases.md",
    "Literature notes/Anaesthesia core notes/Domain 4_ Cardiac_Thoracic_Vascular/Cardiac physiology.md",
    "Literature notes/Anaesthesia core notes/Domain 4_ Cardiac_Thoracic_Vascular/Domain 4_ Topics and links.md",
    "TOE.md"
  ]
}